COPYRIGHT
MANIFEST.in
Makefile
README
setup.py
test/__init__.py
test/__init__.pyc
test/httptest.yaml
test/test_compile.py
test/test_web_http_api.py
test/__pycache__/test_compile.cpython-27-PYTEST.pyc
test/__pycache__/test_web_http_api.cpython-27-PYTEST.pyc
tiddlywebplugins/__init__.py
tiddlywebplugins/socialusers.py
tiddlywebplugins.socialusers.egg-info/PKG-INFO
tiddlywebplugins.socialusers.egg-info/SOURCES.txt
tiddlywebplugins.socialusers.egg-info/dependency_links.txt
tiddlywebplugins.socialusers.egg-info/namespace_packages.txt
tiddlywebplugins.socialusers.egg-info/not-zip-safe
tiddlywebplugins.socialusers.egg-info/requires.txt
tiddlywebplugins.socialusers.egg-info/top_level.txt