Metadata-Version: 1.0
Name: tiddlywebplugins.socialusers
Version: 0.9
Summary: An HTTP way of accessing and creating TiddlyWeb users.
Home-page: http://pypi.python.org/pypi/tiddlywebplugins.socialusers
Author: Chris Dent
Author-email: cdent@peermore.com
License: BSD
Platform: Posix; MacOS X; Windows
